turtle_tools.py
turtle_tools-0.0.1.dist-info/METADATA
turtle_tools-0.0.1.dist-info/WHEEL
turtle_tools-0.0.1.dist-info/RECORD
