Metadata-Version: 2.1
Name: turtle-tools
Version: 0.0.1
Summary: Simple utilities that extend Turtle
Author: Yngve Mardal Moe, Marie Roald
Keywords: education,turtle
Classifier: License :: OSI Approved :: MIT License
Classifier: Operating System :: OS Independent
Classifier: Programming Language :: Python :: 3
Requires-Python: >=3.8
